[
  {
    "source_file": "noviembre 25.pdf",
    "billing_period": "noviembre de 2025",
    "city": "Medellín",
    "stratum": 5,
    "water_m3": 9.0,
    "water_cop": 82054.82,
    "sewer_m3": 9.0,
    "sewer_cop": 59936.47,
    "energy_kwh": 181.0,
    "energy_cop": 193327.55,
    "gas_m3": 9.4,
    "gas_cop": 35866.64,
    "other_entities_cop": 82777.22,
    "estimated_total_cop": 453962.7
  },
  {
    "source_file": "diciembre 25.pdf",
    "billing_period": "diciembre de 2025",
    "city": "Medellín",
    "stratum": 5,
    "water_m3": 10.0,
    "water_cop": 87750.27,
    "sewer_m3": 10.0,
    "sewer_cop": 66788.69,
    "energy_kwh": 175.0,
    "energy_cop": 185986.5,
    "gas_m3": 12.0,
    "gas_cop": 43776.12,
    "other_entities_cop": 79480.06,
    "estimated_total_cop": 463781.64
  },
  {
    "source_file": "enero 26.pdf",
    "billing_period": "enero de 2026",
    "city": "Medellín",
    "stratum": 5,
    "water_m3": 9.0,
    "water_cop": 80467.24,
    "sewer_m3": 9.0,
    "sewer_cop": 60970.98,
    "energy_kwh": 186.0,
    "energy_cop": 192401.73,
    "gas_m3": 9.4,
    "gas_cop": 36338.44,
    "other_entities_cop": 79051.94,
    "estimated_total_cop": 449230.33
  },
  {
    "source_file": "febrero 26.pdf",
    "billing_period": "febrero de 2026",
    "city": "Medellín",
    "stratum": 5,
    "water_m3": 6.0,
    "water_cop": 58561.35,
    "sewer_m3": 6.0,
    "sewer_cop": 43474.61,
    "energy_kwh": 169.0,
    "energy_cop": 174243.73,
    "gas_m3": 6.8,
    "gas_cop": 26707.58,
    "other_entities_cop": 79271.35,
    "estimated_total_cop": 382258.62
  },
  {
    "source_file": "marzo 26.pdf",
    "billing_period": "marzo de 2026",
    "city": "Medellín",
    "stratum": 5,
    "water_m3": 8.0,
    "water_cop": 73155.81,
    "sewer_m3": 8.0,
    "sewer_cop": 55131.65,
    "energy_kwh": 131.0,
    "energy_cop": 135064.67,
    "gas_m3": 6.8,
    "gas_cop": 30258.71,
    "other_entities_cop": 87628.21,
    "estimated_total_cop": 381239.05
  },
  {
    "source_file": "abril 26.pdf",
    "billing_period": "abril de 2026",
    "city": "Medellín",
    "stratum": 5,
    "water_m3": 6.0,
    "water_cop": 58561.35,
    "sewer_m3": 6.0,
    "sewer_cop": 43474.61,
    "energy_kwh": 142.0,
    "energy_cop": 136531.3,
    "gas_m3": 5.9,
    "gas_cop": 27787.7,
    "other_entities_cop": 88165.28,
    "estimated_total_cop": 354520.24
  }
]
